databox/__init__.py
databox/api_client.py
databox/api_response.py
databox/configuration.py
databox/exceptions.py
databox/py.typed
databox/rest.py
databox/api/__init__.py
databox/api/default_api.py
databox/models/__init__.py
databox/models/api_response.py
databox/models/push_data.py
databox/models/push_data_attribute.py
databox/models/state.py
databox-2.2.2.dist-info/METADATA
databox-2.2.2.dist-info/WHEEL
databox-2.2.2.dist-info/top_level.txt
databox-2.2.2.dist-info/RECORD
