Metadata-Version: 2.1
Name: databox
Version: 2.2.2
Summary: Static OpenAPI document of Push API resource
Home-page: https://github.com/databox/databox-python
Author: OpenAPI Generator community
Author-email: team@openapitools.org
Keywords: OpenAPI,OpenAPI-Generator,Static OpenAPI document of Push API resource
Requires-Dist: urllib3 <2.1.0,>=1.25.3
Requires-Dist: python-dateutil
Requires-Dist: pydantic >=2
Requires-Dist: typing-extensions >=4.7.1
